<?xml version="1.0" encoding="utf-8" ?>
<dwsync>
<file name="Comment.tpl" server="www.ezbank.com.vn//public_html/ezwork/" local="131114437666701597" remote="131112784800000000" Dst="0" />
<file name="Currency.tpl" server="www.ezbank.com.vn//public_html/ezwork/" local="131114437666776656" remote="131112784800000000" Dst="0" />
<file name="Discount.tpl" server="www.ezbank.com.vn//public_html/ezwork/" local="131114437666791664" remote="131112784800000000" Dst="0" />
<file name="DiscountMode.tpl" server="www.ezbank.com.vn//public_html/ezwork/" local="131114437668529463" remote="131112784800000000" Dst="0" />
<file name="GrossPrice.tpl" server="www.ezbank.com.vn//public_html/ezwork/" local="131114437668549491" remote="131112784800000000" Dst="0" />
<file name="ItemNumber.tpl" server="www.ezbank.com.vn//public_html/ezwork/" local="131114437668649556" remote="131112784800000000" Dst="0" />
<file name="Margin.tpl" server="www.ezbank.com.vn//public_html/ezwork/" local="131114437670262677" remote="131112784800000000" Dst="0" />
<file name="MarginP.tpl" server="www.ezbank.com.vn//public_html/ezwork/" local="131114437670272690" remote="131112784800000000" Dst="0" />
<file name="Name.tpl" server="www.ezbank.com.vn//public_html/ezwork/" local="131114437670352741" remote="131112784800000000" Dst="0" />
<file name="NetPrice.tpl" server="www.ezbank.com.vn//public_html/ezwork/" local="131114437672024604" remote="131112784800000000" Dst="0" />
<file name="PicklistField.tpl" server="www.ezbank.com.vn//public_html/ezwork/" local="131114437672084652" remote="131112784800000000" Dst="0" />
<file name="Purchase.tpl" server="www.ezbank.com.vn//public_html/ezwork/" local="131114437672104670" remote="131112784800000000" Dst="0" />
<file name="Quantity.tpl" server="www.ezbank.com.vn//public_html/ezwork/" local="131114437674176429" remote="131112784800000000" Dst="0" />
<file name="Reference.tpl" server="www.ezbank.com.vn//public_html/ezwork/" local="131114437674256486" remote="131112784800000000" Dst="0" />
<file name="Tax.tpl" server="www.ezbank.com.vn//public_html/ezwork/" local="131114437674266505" remote="131112784800000000" Dst="0" />
<file name="TaxMode.tpl" server="www.ezbank.com.vn//public_html/ezwork/" local="131114437676393073" remote="131112784800000000" Dst="0" />
<file name="TotalPrice.tpl" server="www.ezbank.com.vn//public_html/ezwork/" local="131114437676413093" remote="131112784800000000" Dst="0" />
<file name="UnitPrice.tpl" server="www.ezbank.com.vn//public_html/ezwork/" local="131114437676433107" remote="131112784800000000" Dst="0" />
<file name="Value.tpl" server="www.ezbank.com.vn//public_html/ezwork/" local="131114437679215520" remote="131112784800000000" Dst="0" />
</dwsync>