<?xml version="1.0" encoding="utf-8" ?>
<dwsync>
<file name=".htaccess" server="www.ezbank.com.vn//public_html/ezwork/" local="131114440639083369" remote="131112784800000000" Dst="0" />
<file name="af.php" server="www.ezbank.com.vn//public_html/ezwork/" local="131114440641144919" remote="131112784800000000" Dst="0" />
<file name="bg.php" server="www.ezbank.com.vn//public_html/ezwork/" local="131114440641515182" remote="131112784800000000" Dst="0" />
<file name="ca.php" server="www.ezbank.com.vn//public_html/ezwork/" local="131114440641325050" remote="131112784800000000" Dst="0" />
<file name="cs.php" server="www.ezbank.com.vn//public_html/ezwork/" local="131114440643168214" remote="131112784800000000" Dst="0" />
<file name="da.php" server="www.ezbank.com.vn//public_html/ezwork/" local="131114440643338330" remote="131112784800000000" Dst="0" />
<file name="de.php" server="www.ezbank.com.vn//public_html/ezwork/" local="131114440643538480" remote="131112784800000000" Dst="0" />
<file name="el.php" server="www.ezbank.com.vn//public_html/ezwork/" local="131114440645195193" remote="131112784800000000" Dst="0" />
<file name="en.php" server="www.ezbank.com.vn//public_html/ezwork/" local="131114440645375327" remote="131112784800000000" Dst="0" />
<file name="es.php" server="www.ezbank.com.vn//public_html/ezwork/" local="131114440645545442" remote="131112784800000000" Dst="0" />
<file name="et.php" server="www.ezbank.com.vn//public_html/ezwork/" local="131114440646696345" remote="131112784800000000" Dst="0" />
<file name="fa.php" server="www.ezbank.com.vn//public_html/ezwork/" local="131114440647317855" remote="131112784800000000" Dst="0" />
<file name="fi.php" server="www.ezbank.com.vn//public_html/ezwork/" local="131114440647487968" remote="131112784800000000" Dst="0" />
<file name="fr.php" server="www.ezbank.com.vn//public_html/ezwork/" local="131114440649075067" remote="131112784800000000" Dst="0" />
<file name="he.php" server="www.ezbank.com.vn//public_html/ezwork/" local="131114440649265202" remote="131112784800000000" Dst="0" />
<file name="hu.php" server="www.ezbank.com.vn//public_html/ezwork/" local="131114440649425310" remote="131112784800000000" Dst="0" />
<file name="id.php" server="www.ezbank.com.vn//public_html/ezwork/" local="131114440651023163" remote="131112784800000000" Dst="0" />
<file name="it.php" server="www.ezbank.com.vn//public_html/ezwork/" local="131114440651463462" remote="131112784800000000" Dst="0" />
<file name="ja.php" server="www.ezbank.com.vn//public_html/ezwork/" local="131114440651243305" remote="131112784800000000" Dst="0" />
<file name="lt.php" server="www.ezbank.com.vn//public_html/ezwork/" local="131114440653120941" remote="131112784800000000" Dst="0" />
<file name="lv.php" server="www.ezbank.com.vn//public_html/ezwork/" local="131114440653441175" remote="131112784800000000" Dst="0" />
<file name="nl.php" server="www.ezbank.com.vn//public_html/ezwork/" local="131114440653251048" remote="131112784800000000" Dst="0" />
<file name="no.php" server="www.ezbank.com.vn//public_html/ezwork/" local="131114440655132513" remote="131112784800000000" Dst="0" />
<file name="pl.php" server="www.ezbank.com.vn//public_html/ezwork/" local="131114440655312664" remote="131112784800000000" Dst="0" />
<file name="pt-br.php" server="www.ezbank.com.vn//public_html/ezwork/" local="131114440655462736" remote="131112784800000000" Dst="0" />
<file name="pt.php" server="www.ezbank.com.vn//public_html/ezwork/" local="131114440656639199" remote="131112784800000000" Dst="0" />
<file name="ro.php" server="www.ezbank.com.vn//public_html/ezwork/" local="131114440657240575" remote="131112784800000000" Dst="0" />
<file name="ru.php" server="www.ezbank.com.vn//public_html/ezwork/" local="131114440657450742" remote="131112784800000000" Dst="0" />
<file name="sk.php" server="www.ezbank.com.vn//public_html/ezwork/" local="131114440659363095" remote="131112784800000000" Dst="0" />
<file name="sv.php" server="www.ezbank.com.vn//public_html/ezwork/" local="131114440659533218" remote="131112784800000000" Dst="0" />
<file name="tr.php" server="www.ezbank.com.vn//public_html/ezwork/" local="131114440659683394" remote="131112784800000000" Dst="0" />
<file name="uk.php" server="www.ezbank.com.vn//public_html/ezwork/" local="131114440661159548" remote="131112784800000000" Dst="0" />
<file name="vi.php" server="www.ezbank.com.vn//public_html/ezwork/" local="131114440661900142" remote="131112784800000000" Dst="0" />
<file name="zh-cn.php" server="www.ezbank.com.vn//public_html/ezwork/" local="131114440662120305" remote="131112784800000000" Dst="0" />
</dwsync>